TOPSIS_package/cli.py
topsis_asharma_3027-1.0.dist-info/METADATA
topsis_asharma_3027-1.0.dist-info/WHEEL
topsis_asharma_3027-1.0.dist-info/entry_points.txt
topsis_asharma_3027-1.0.dist-info/top_level.txt
topsis_asharma_3027-1.0.dist-info/RECORD
