Metadata-Version: 2.1
Name: topsis-asharma-3027
Version: 1.0
Summary: Topsis analysis of a csv file
Home-page: UNKNOWN
Author: abhishek sharma
Author-email: asharma1_be17@thapar.edu
License: MIT
Platform: UNKNOWN
Classifier: License :: OSI Approved :: MIT License
Classifier: Programming Language :: Python :: 3
Classifier: Programming Language :: Python :: 3.7
Requires-Dist: numpy
Requires-Dist: pandas
